[
  {
    "title": "Solar Wind Plasma - 2026-03-08 23:59:00.000",
    "content": "Density: 2.78 p/cc, Speed: 480.8 km/s, Temperature: 88281 K",
    "timestamp": "2026-03-08 23:59:00.000",
    "source": "NOAA SWPC Solar Wind Plasma 7-day",
    "confidence": 0.92
  },
  {
    "title": "Solar Wind Plasma - 2026-03-09 00:00:00.000",
    "content": "Density: 2.72 p/cc, Speed: 479.3 km/s, Temperature: 86049 K",
    "timestamp": "2026-03-09 00:00:00.000",
    "source": "NOAA SWPC Solar Wind Plasma 7-day",
    "confidence": 0.92
  },
  {
    "title": "Solar Wind Plasma - 2026-03-09 00:01:00.000",
    "content": "Density: 2.57 p/cc, Speed: 478.3 km/s, Temperature: 87956 K",
    "timestamp": "2026-03-09 00:01:00.000",
    "source": "NOAA SWPC Solar Wind Plasma 7-day",
    "confidence": 0.92
  },
  {
    "title": "Solar Wind Plasma - 2026-03-09 00:02:00.000",
    "content": "Density: 2.76 p/cc, Speed: 478.9 km/s, Temperature: 82273 K",
    "timestamp": "2026-03-09 00:02:00.000",
    "source": "NOAA SWPC Solar Wind Plasma 7-day",
    "confidence": 0.92
  },
  {
    "title": "Solar Wind Plasma - 2026-03-09 00:03:00.000",
    "content": "Density: 2.81 p/cc, Speed: 480.0 km/s, Temperature: 77100 K",
    "timestamp": "2026-03-09 00:03:00.000",
    "source": "NOAA SWPC Solar Wind Plasma 7-day",
    "confidence": 0.92
  },
  {
    "title": "Solar Wind Plasma - 2026-03-09 00:04:00.000",
    "content": "Density: 2.85 p/cc, Speed: 479.1 km/s, Temperature: 77504 K",
    "timestamp": "2026-03-09 00:04:00.000",
    "source": "NOAA SWPC Solar Wind Plasma 7-day",
    "confidence": 0.92
  },
  {
    "title": "Solar Wind Plasma - 2026-03-09 00:05:00.000",
    "content": "Density: 2.73 p/cc, Speed: 480.4 km/s, Temperature: 79304 K",
    "timestamp": "2026-03-09 00:05:00.000",
    "source": "NOAA SWPC Solar Wind Plasma 7-day",
    "confidence": 0.92
  },
  {
    "title": "Solar Wind Plasma - 2026-03-09 00:06:00.000",
    "content": "Density: 2.87 p/cc, Speed: 480.6 km/s, Temperature: 75818 K",
    "timestamp": "2026-03-09 00:06:00.000",
    "source": "NOAA SWPC Solar Wind Plasma 7-day",
    "confidence": 0.92
  },
  {
    "title": "Solar Wind Plasma - 2026-03-09 00:07:00.000",
    "content": "Density: 2.82 p/cc, Speed: 482.2 km/s, Temperature: 76618 K",
    "timestamp": "2026-03-09 00:07:00.000",
    "source": "NOAA SWPC Solar Wind Plasma 7-day",
    "confidence": 0.92
  },
  {
    "title": "Solar Wind Plasma - 2026-03-09 00:08:00.000",
    "content": "Density: 2.62 p/cc, Speed: 484.7 km/s, Temperature: 84694 K",
    "timestamp": "2026-03-09 00:08:00.000",
    "source": "NOAA SWPC Solar Wind Plasma 7-day",
    "confidence": 0.92
  },
  {
    "title": "Solar Wind Plasma - 2026-03-09 00:09:00.000",
    "content": "Density: 2.75 p/cc, Speed: 484.6 km/s, Temperature: 79815 K",
    "timestamp": "2026-03-09 00:09:00.000",
    "source": "NOAA SWPC Solar Wind Plasma 7-day",
    "confidence": 0.92
  },
  {
    "title": "Solar Wind Plasma - 2026-03-09 00:10:00.000",
    "content": "Density: 2.96 p/cc, Speed: 483.9 km/s, Temperature: 81052 K",
    "timestamp": "2026-03-09 00:10:00.000",
    "source": "NOAA SWPC Solar Wind Plasma 7-day",
    "confidence": 0.92
  },
  {
    "title": "Solar Wind Plasma - 2026-03-09 00:11:00.000",
    "content": "Density: 2.90 p/cc, Speed: 487.4 km/s, Temperature: 73888 K",
    "timestamp": "2026-03-09 00:11:00.000",
    "source": "NOAA SWPC Solar Wind Plasma 7-day",
    "confidence": 0.92
  },
  {
    "title": "Solar Wind Plasma - 2026-03-09 00:12:00.000",
    "content": "Density: 2.96 p/cc, Speed: 485.1 km/s, Temperature: 77223 K",
    "timestamp": "2026-03-09 00:12:00.000",
    "source": "NOAA SWPC Solar Wind Plasma 7-day",
    "confidence": 0.92
  },
  {
    "title": "Solar Wind Plasma - 2026-03-09 00:13:00.000",
    "content": "Density: 2.91 p/cc, Speed: 484.9 km/s, Temperature: 77535 K",
    "timestamp": "2026-03-09 00:13:00.000",
    "source": "NOAA SWPC Solar Wind Plasma 7-day",
    "confidence": 0.92
  },
  {
    "title": "Solar Wind Plasma - 2026-03-09 00:14:00.000",
    "content": "Density: 2.11 p/cc, Speed: 487.0 km/s, Temperature: 112115 K",
    "timestamp": "2026-03-09 00:14:00.000",
    "source": "NOAA SWPC Solar Wind Plasma 7-day",
    "confidence": 0.92
  },
  {
    "title": "Solar Wind Plasma - 2026-03-09 00:15:00.000",
    "content": "Density: 1.86 p/cc, Speed: 486.2 km/s, Temperature: 117351 K",
    "timestamp": "2026-03-09 00:15:00.000",
    "source": "NOAA SWPC Solar Wind Plasma 7-day",
    "confidence": 0.92
  },
  {
    "title": "Solar Wind Plasma - 2026-03-09 00:16:00.000",
    "content": "Density: 2.44 p/cc, Speed: 483.3 km/s, Temperature: 94647 K",
    "timestamp": "2026-03-09 00:16:00.000",
    "source": "NOAA SWPC Solar Wind Plasma 7-day",
    "confidence": 0.92
  },
  {
    "title": "Solar Wind Plasma - 2026-03-09 00:17:00.000",
    "content": "Density: 2.92 p/cc, Speed: 481.3 km/s, Temperature: 80409 K",
    "timestamp": "2026-03-09 00:17:00.000",
    "source": "NOAA SWPC Solar Wind Plasma 7-day",
    "confidence": 0.92
  },
  {
    "title": "Solar Wind Plasma - 2026-03-09 00:18:00.000",
    "content": "Density: 2.95 p/cc, Speed: 481.0 km/s, Temperature: 76332 K",
    "timestamp": "2026-03-09 00:18:00.000",
    "source": "NOAA SWPC Solar Wind Plasma 7-day",
    "confidence": 0.92
  },
  {
    "title": "Solar Wind Plasma - 2026-03-09 00:19:00.000",
    "content": "Density: 2.85 p/cc, Speed: 482.0 km/s, Temperature: 87981 K",
    "timestamp": "2026-03-09 00:19:00.000",
    "source": "NOAA SWPC Solar Wind Plasma 7-day",
    "confidence": 0.92
  },
  {
    "title": "Solar Wind Plasma - 2026-03-09 00:20:00.000",
    "content": "Density: 2.85 p/cc, Speed: 482.9 km/s, Temperature: 89791 K",
    "timestamp": "2026-03-09 00:20:00.000",
    "source": "NOAA SWPC Solar Wind Plasma 7-day",
    "confidence": 0.92
  },
  {
    "title": "Solar Wind Plasma - 2026-03-09 00:21:00.000",
    "content": "Density: 2.77 p/cc, Speed: 481.1 km/s, Temperature: 95782 K",
    "timestamp": "2026-03-09 00:21:00.000",
    "source": "NOAA SWPC Solar Wind Plasma 7-day",
    "confidence": 0.92
  },
  {
    "title": "Solar Wind Plasma - 2026-03-09 00:22:00.000",
    "content": "Density: 2.94 p/cc, Speed: 480.3 km/s, Temperature: 80369 K",
    "timestamp": "2026-03-09 00:22:00.000",
    "source": "NOAA SWPC Solar Wind Plasma 7-day",
    "confidence": 0.92
  },
  {
    "title": "Solar Wind Plasma - 2026-03-09 00:23:00.000",
    "content": "Density: 2.96 p/cc, Speed: 481.6 km/s, Temperature: 68189 K",
    "timestamp": "2026-03-09 00:23:00.000",
    "source": "NOAA SWPC Solar Wind Plasma 7-day",
    "confidence": 0.92
  },
  {
    "title": "Solar Wind Plasma - 2026-03-09 00:24:00.000",
    "content": "Density: 2.70 p/cc, Speed: 480.7 km/s, Temperature: 86589 K",
    "timestamp": "2026-03-09 00:24:00.000",
    "source": "NOAA SWPC Solar Wind Plasma 7-day",
    "confidence": 0.92
  },
  {
    "title": "Solar Wind Plasma - 2026-03-09 00:25:00.000",
    "content": "Density: 2.93 p/cc, Speed: 480.3 km/s, Temperature: 90118 K",
    "timestamp": "2026-03-09 00:25:00.000",
    "source": "NOAA SWPC Solar Wind Plasma 7-day",
    "confidence": 0.92
  },
  {
    "title": "Solar Wind Plasma - 2026-03-09 00:26:00.000",
    "content": "Density: 2.96 p/cc, Speed: 480.6 km/s, Temperature: 87050 K",
    "timestamp": "2026-03-09 00:26:00.000",
    "source": "NOAA SWPC Solar Wind Plasma 7-day",
    "confidence": 0.92
  },
  {
    "title": "Solar Wind Plasma - 2026-03-09 00:27:00.000",
    "content": "Density: 2.96 p/cc, Speed: 480.6 km/s, Temperature: 86539 K",
    "timestamp": "2026-03-09 00:27:00.000",
    "source": "NOAA SWPC Solar Wind Plasma 7-day",
    "confidence": 0.92
  },
  {
    "title": "Solar Wind Plasma - 2026-03-09 00:28:00.000",
    "content": "Density: 2.77 p/cc, Speed: 480.8 km/s, Temperature: 92619 K",
    "timestamp": "2026-03-09 00:28:00.000",
    "source": "NOAA SWPC Solar Wind Plasma 7-day",
    "confidence": 0.92
  },
  {
    "title": "Solar Wind Plasma - 2026-03-09 00:29:00.000",
    "content": "Density: 2.87 p/cc, Speed: 480.4 km/s, Temperature: 93716 K",
    "timestamp": "2026-03-09 00:29:00.000",
    "source": "NOAA SWPC Solar Wind Plasma 7-day",
    "confidence": 0.92
  },
  {
    "title": "Solar Wind Plasma - 2026-03-09 00:30:00.000",
    "content": "Density: 2.80 p/cc, Speed: 479.6 km/s, Temperature: 89107 K",
    "timestamp": "2026-03-09 00:30:00.000",
    "source": "NOAA SWPC Solar Wind Plasma 7-day",
    "confidence": 0.92
  },
  {
    "title": "Solar Wind Plasma - 2026-03-09 00:31:00.000",
    "content": "Density: 2.98 p/cc, Speed: 479.9 km/s, Temperature: 84181 K",
    "timestamp": "2026-03-09 00:31:00.000",
    "source": "NOAA SWPC Solar Wind Plasma 7-day",
    "confidence": 0.92
  },
  {
    "title": "Solar Wind Plasma - 2026-03-09 00:32:00.000",
    "content": "Density: 2.90 p/cc, Speed: 482.0 km/s, Temperature: 80108 K",
    "timestamp": "2026-03-09 00:32:00.000",
    "source": "NOAA SWPC Solar Wind Plasma 7-day",
    "confidence": 0.92
  },
  {
    "title": "Solar Wind Plasma - 2026-03-09 00:33:00.000",
    "content": "Density: 2.46 p/cc, Speed: 488.1 km/s, Temperature: 74621 K",
    "timestamp": "2026-03-09 00:33:00.000",
    "source": "NOAA SWPC Solar Wind Plasma 7-day",
    "confidence": 0.92
  },
  {
    "title": "Solar Wind Plasma - 2026-03-09 00:34:00.000",
    "content": "Density: 2.51 p/cc, Speed: 492.7 km/s, Temperature: 78973 K",
    "timestamp": "2026-03-09 00:34:00.000",
    "source": "NOAA SWPC Solar Wind Plasma 7-day",
    "confidence": 0.92
  },
  {
    "title": "Solar Wind Plasma - 2026-03-09 00:35:00.000",
    "content": "Density: 2.75 p/cc, Speed: 486.6 km/s, Temperature: 96568 K",
    "timestamp": "2026-03-09 00:35:00.000",
    "source": "NOAA SWPC Solar Wind Plasma 7-day",
    "confidence": 0.92
  },
  {
    "title": "Solar Wind Plasma - 2026-03-09 00:36:00.000",
    "content": "Density: 2.44 p/cc, Speed: 482.3 km/s, Temperature: 102063 K",
    "timestamp": "2026-03-09 00:36:00.000",
    "source": "NOAA SWPC Solar Wind Plasma 7-day",
    "confidence": 0.92
  },
  {
    "title": "Solar Wind Plasma - 2026-03-09 00:37:00.000",
    "content": "Density: 2.16 p/cc, Speed: 485.0 km/s, Temperature: 100433 K",
    "timestamp": "2026-03-09 00:37:00.000",
    "source": "NOAA SWPC Solar Wind Plasma 7-day",
    "confidence": 0.92
  },
  {
    "title": "Solar Wind Plasma - 2026-03-09 00:38:00.000",
    "content": "Density: 2.85 p/cc, Speed: 485.3 km/s, Temperature: 85289 K",
    "timestamp": "2026-03-09 00:38:00.000",
    "source": "NOAA SWPC Solar Wind Plasma 7-day",
    "confidence": 0.92
  },
  {
    "title": "Solar Wind Plasma - 2026-03-09 00:39:00.000",
    "content": "Density: 2.86 p/cc, Speed: 480.6 km/s, Temperature: 87013 K",
    "timestamp": "2026-03-09 00:39:00.000",
    "source": "NOAA SWPC Solar Wind Plasma 7-day",
    "confidence": 0.92
  },
  {
    "title": "Solar Wind Plasma - 2026-03-09 00:40:00.000",
    "content": "Density: 3.24 p/cc, Speed: 479.9 km/s, Temperature: 83523 K",
    "timestamp": "2026-03-09 00:40:00.000",
    "source": "NOAA SWPC Solar Wind Plasma 7-day",
    "confidence": 0.92
  },
  {
    "title": "Solar Wind Plasma - 2026-03-09 00:41:00.000",
    "content": "Density: 2.56 p/cc, Speed: 481.0 km/s, Temperature: 90776 K",
    "timestamp": "2026-03-09 00:41:00.000",
    "source": "NOAA SWPC Solar Wind Plasma 7-day",
    "confidence": 0.92
  },
  {
    "title": "Solar Wind Plasma - 2026-03-09 00:42:00.000",
    "content": "Density: 3.01 p/cc, Speed: 479.5 km/s, Temperature: 91796 K",
    "timestamp": "2026-03-09 00:42:00.000",
    "source": "NOAA SWPC Solar Wind Plasma 7-day",
    "confidence": 0.92
  },
  {
    "title": "Solar Wind Plasma - 2026-03-09 00:43:00.000",
    "content": "Density: 2.99 p/cc, Speed: 479.8 km/s, Temperature: 90928 K",
    "timestamp": "2026-03-09 00:43:00.000",
    "source": "NOAA SWPC Solar Wind Plasma 7-day",
    "confidence": 0.92
  },
  {
    "title": "Solar Wind Plasma - 2026-03-09 00:44:00.000",
    "content": "Density: 3.04 p/cc, Speed: 478.8 km/s, Temperature: 88438 K",
    "timestamp": "2026-03-09 00:44:00.000",
    "source": "NOAA SWPC Solar Wind Plasma 7-day",
    "confidence": 0.92
  },
  {
    "title": "Solar Wind Plasma - 2026-03-09 00:45:00.000",
    "content": "Density: 2.94 p/cc, Speed: 479.2 km/s, Temperature: 86035 K",
    "timestamp": "2026-03-09 00:45:00.000",
    "source": "NOAA SWPC Solar Wind Plasma 7-day",
    "confidence": 0.92
  },
  {
    "title": "Solar Wind Plasma - 2026-03-09 00:46:00.000",
    "content": "Density: 3.08 p/cc, Speed: 477.8 km/s, Temperature: 85156 K",
    "timestamp": "2026-03-09 00:46:00.000",
    "source": "NOAA SWPC Solar Wind Plasma 7-day",
    "confidence": 0.92
  },
  {
    "title": "Solar Wind Plasma - 2026-03-09 00:47:00.000",
    "content": "Density: 3.17 p/cc, Speed: 478.5 km/s, Temperature: 86673 K",
    "timestamp": "2026-03-09 00:47:00.000",
    "source": "NOAA SWPC Solar Wind Plasma 7-day",
    "confidence": 0.92
  },
  {
    "title": "Solar Wind Plasma - 2026-03-09 00:48:00.000",
    "content": "Density: 3.16 p/cc, Speed: 479.3 km/s, Temperature: 91925 K",
    "timestamp": "2026-03-09 00:48:00.000",
    "source": "NOAA SWPC Solar Wind Plasma 7-day",
    "confidence": 0.92
  }
]